{
  "metadata": {
    "source_file": "data-to-convert/Goodpaster River Historical/Yukon Escapement Daily Chart.xlsx",
    "conversion_date": "2025-09-30T16:56:01.769910",
    "location": "Goodpaster River Escapement",
    "location_id": "5016-goodpaster-river-escapement",
    "species": "Chinook Salmon",
    "species_id": "410",
    "method": "weir",
    "region": "Yukon",
    "total_records": 25,
    "date_range": {
      "start": "2009-06-01",
      "end": "2009-09-30"
    },
    "adfg_species_code": "K",
    "confidence_interval": "95%"
  },
  "DATA": [
    {
      "date": "2009-07/07",
      "count": 0,
      "species": "Chinook Salmon",
      "species_id": "410",
      "adfg_species_code": "K",
      "location": "Goodpaster River Escapement",
      "location_id": "5016-goodpaster-river-escapement",
      "method": "weir",
      "region": "Yukon",
      "gps": [
        64.5,
        -165.0
      ],
      "notes": "Commercial data from Yukon Escapement Daily Chart.xlsx"
    },
    {
      "date": "2009-07/08",
      "count": 3,
      "species": "Chinook Salmon",
      "species_id": "410",
      "adfg_species_code": "K",
      "location": "Goodpaster River Escapement",
      "location_id": "5016-goodpaster-river-escapement",
      "method": "weir",
      "region": "Yukon",
      "gps": [
        64.5,
        -165.0
      ],
      "notes": "Commercial data from Yukon Escapement Daily Chart.xlsx"
    },
    {
      "date": "2009-07/09",
      "count": 18,
      "species": "Chinook Salmon",
      "species_id": "410",
      "adfg_species_code": "K",
      "location": "Goodpaster River Escapement",
      "location_id": "5016-goodpaster-river-escapement",
      "method": "weir",
      "region": "Yukon",
      "gps": [
        64.5,
        -165.0
      ],
      "notes": "Commercial data from Yukon Escapement Daily Chart.xlsx"
    },
    {
      "date": "2009-07/10",
      "count": 24,
      "species": "Chinook Salmon",
      "species_id": "410",
      "adfg_species_code": "K",
      "location": "Goodpaster River Escapement",
      "location_id": "5016-goodpaster-river-escapement",
      "method": "weir",
      "region": "Yukon",
      "gps": [
        64.5,
        -165.0
      ],
      "notes": "Commercial data from Yukon Escapement Daily Chart.xlsx"
    },
    {
      "date": "2009-07/11",
      "count": 66,
      "species": "Chinook Salmon",
      "species_id": "410",
      "adfg_species_code": "K",
      "location": "Goodpaster River Escapement",
      "location_id": "5016-goodpaster-river-escapement",
      "method": "weir",
      "region": "Yukon",
      "gps": [
        64.5,
        -165.0
      ],
      "notes": "Commercial data from Yukon Escapement Daily Chart.xlsx"
    },
    {
      "date": "2009-07/12",
      "count": 108,
      "species": "Chinook Salmon",
      "species_id": "410",
      "adfg_species_code": "K",
      "location": "Goodpaster River Escapement",
      "location_id": "5016-goodpaster-river-escapement",
      "method": "weir",
      "region": "Yukon",
      "gps": [
        64.5,
        -165.0
      ],
      "notes": "Commercial data from Yukon Escapement Daily Chart.xlsx"
    },
    {
      "date": "2009-07/13",
      "count": 45,
      "species": "Chinook Salmon",
      "species_id": "410",
      "adfg_species_code": "K",
      "location": "Goodpaster River Escapement",
      "location_id": "5016-goodpaster-river-escapement",
      "method": "weir",
      "region": "Yukon",
      "gps": [
        64.5,
        -165.0
      ],
      "notes": "Commercial data from Yukon Escapement Daily Chart.xlsx"
    },
    {
      "date": "2009-07/14",
      "count": 138,
      "species": "Chinook Salmon",
      "species_id": "410",
      "adfg_species_code": "K",
      "location": "Goodpaster River Escapement",
      "location_id": "5016-goodpaster-river-escapement",
      "method": "weir",
      "region": "Yukon",
      "gps": [
        64.5,
        -165.0
      ],
      "notes": "Commercial data from Yukon Escapement Daily Chart.xlsx"
    },
    {
      "date": "2009-07/15",
      "count": 171,
      "species": "Chinook Salmon",
      "species_id": "410",
      "adfg_species_code": "K",
      "location": "Goodpaster River Escapement",
      "location_id": "5016-goodpaster-river-escapement",
      "method": "weir",
      "region": "Yukon",
      "gps": [
        64.5,
        -165.0
      ],
      "notes": "Commercial data from Yukon Escapement Daily Chart.xlsx"
    },
    {
      "date": "2009-07/16",
      "count": 198,
      "species": "Chinook Salmon",
      "species_id": "410",
      "adfg_species_code": "K",
      "location": "Goodpaster River Escapement",
      "location_id": "5016-goodpaster-river-escapement",
      "method": "weir",
      "region": "Yukon",
      "gps": [
        64.5,
        -165.0
      ],
      "notes": "Commercial data from Yukon Escapement Daily Chart.xlsx"
    },
    {
      "date": "2009-07/17",
      "count": 300,
      "species": "Chinook Salmon",
      "species_id": "410",
      "adfg_species_code": "K",
      "location": "Goodpaster River Escapement",
      "location_id": "5016-goodpaster-river-escapement",
      "method": "weir",
      "region": "Yukon",
      "gps": [
        64.5,
        -165.0
      ],
      "notes": "Commercial data from Yukon Escapement Daily Chart.xlsx"
    },
    {
      "date": "2009-07/18",
      "count": 309,
      "species": "Chinook Salmon",
      "species_id": "410",
      "adfg_species_code": "K",
      "location": "Goodpaster River Escapement",
      "location_id": "5016-goodpaster-river-escapement",
      "method": "weir",
      "region": "Yukon",
      "gps": [
        64.5,
        -165.0
      ],
      "notes": "Commercial data from Yukon Escapement Daily Chart.xlsx"
    },
    {
      "date": "2009-07/19",
      "count": 234,
      "species": "Chinook Salmon",
      "species_id": "410",
      "adfg_species_code": "K",
      "location": "Goodpaster River Escapement",
      "location_id": "5016-goodpaster-river-escapement",
      "method": "weir",
      "region": "Yukon",
      "gps": [
        64.5,
        -165.0
      ],
      "notes": "Commercial data from Yukon Escapement Daily Chart.xlsx"
    },
    {
      "date": "2009-07/20",
      "count": 378,
      "species": "Chinook Salmon",
      "species_id": "410",
      "adfg_species_code": "K",
      "location": "Goodpaster River Escapement",
      "location_id": "5016-goodpaster-river-escapement",
      "method": "weir",
      "region": "Yukon",
      "gps": [
        64.5,
        -165.0
      ],
      "notes": "Commercial data from Yukon Escapement Daily Chart.xlsx"
    },
    {
      "date": "2009-07/21",
      "count": 276,
      "species": "Chinook Salmon",
      "species_id": "410",
      "adfg_species_code": "K",
      "location": "Goodpaster River Escapement",
      "location_id": "5016-goodpaster-river-escapement",
      "method": "weir",
      "region": "Yukon",
      "gps": [
        64.5,
        -165.0
      ],
      "notes": "Commercial data from Yukon Escapement Daily Chart.xlsx"
    },
    {
      "date": "2009-07/22",
      "count": 321,
      "species": "Chinook Salmon",
      "species_id": "410",
      "adfg_species_code": "K",
      "location": "Goodpaster River Escapement",
      "location_id": "5016-goodpaster-river-escapement",
      "method": "weir",
      "region": "Yukon",
      "gps": [
        64.5,
        -165.0
      ],
      "notes": "Commercial data from Yukon Escapement Daily Chart.xlsx"
    },
    {
      "date": "2009-07/23",
      "count": 225,
      "species": "Chinook Salmon",
      "species_id": "410",
      "adfg_species_code": "K",
      "location": "Goodpaster River Escapement",
      "location_id": "5016-goodpaster-river-escapement",
      "method": "weir",
      "region": "Yukon",
      "gps": [
        64.5,
        -165.0
      ],
      "notes": "Commercial data from Yukon Escapement Daily Chart.xlsx"
    },
    {
      "date": "2009-07/24",
      "count": 216,
      "species": "Chinook Salmon",
      "species_id": "410",
      "adfg_species_code": "K",
      "location": "Goodpaster River Escapement",
      "location_id": "5016-goodpaster-river-escapement",
      "method": "weir",
      "region": "Yukon",
      "gps": [
        64.5,
        -165.0
      ],
      "notes": "Commercial data from Yukon Escapement Daily Chart.xlsx"
    },
    {
      "date": "2009-07/25",
      "count": 216,
      "species": "Chinook Salmon",
      "species_id": "410",
      "adfg_species_code": "K",
      "location": "Goodpaster River Escapement",
      "location_id": "5016-goodpaster-river-escapement",
      "method": "weir",
      "region": "Yukon",
      "gps": [
        64.5,
        -165.0
      ],
      "notes": "Commercial data from Yukon Escapement Daily Chart.xlsx"
    },
    {
      "date": "2009-07/26",
      "count": 201,
      "species": "Chinook Salmon",
      "species_id": "410",
      "adfg_species_code": "K",
      "location": "Goodpaster River Escapement",
      "location_id": "5016-goodpaster-river-escapement",
      "method": "weir",
      "region": "Yukon",
      "gps": [
        64.5,
        -165.0
      ],
      "notes": "Commercial data from Yukon Escapement Daily Chart.xlsx"
    },
    {
      "date": "2009-07/27",
      "count": 231,
      "species": "Chinook Salmon",
      "species_id": "410",
      "adfg_species_code": "K",
      "location": "Goodpaster River Escapement",
      "location_id": "5016-goodpaster-river-escapement",
      "method": "weir",
      "region": "Yukon",
      "gps": [
        64.5,
        -165.0
      ],
      "notes": "Commercial data from Yukon Escapement Daily Chart.xlsx"
    },
    {
      "date": "2009-07/28",
      "count": 147,
      "species": "Chinook Salmon",
      "species_id": "410",
      "adfg_species_code": "K",
      "location": "Goodpaster River Escapement",
      "location_id": "5016-goodpaster-river-escapement",
      "method": "weir",
      "region": "Yukon",
      "gps": [
        64.5,
        -165.0
      ],
      "notes": "Commercial data from Yukon Escapement Daily Chart.xlsx"
    },
    {
      "date": "2009-07/29",
      "count": 111,
      "species": "Chinook Salmon",
      "species_id": "410",
      "adfg_species_code": "K",
      "location": "Goodpaster River Escapement",
      "location_id": "5016-goodpaster-river-escapement",
      "method": "weir",
      "region": "Yukon",
      "gps": [
        64.5,
        -165.0
      ],
      "notes": "Commercial data from Yukon Escapement Daily Chart.xlsx"
    },
    {
      "date": "2009-07/30",
      "count": 123,
      "species": "Chinook Salmon",
      "species_id": "410",
      "adfg_species_code": "K",
      "location": "Goodpaster River Escapement",
      "location_id": "5016-goodpaster-river-escapement",
      "method": "weir",
      "region": "Yukon",
      "gps": [
        64.5,
        -165.0
      ],
      "notes": "Commercial data from Yukon Escapement Daily Chart.xlsx"
    },
    {
      "date": "2009-07/31",
      "count": 48,
      "species": "Chinook Salmon",
      "species_id": "410",
      "adfg_species_code": "K",
      "location": "Goodpaster River Escapement",
      "location_id": "5016-goodpaster-river-escapement",
      "method": "weir",
      "region": "Yukon",
      "gps": [
        64.5,
        -165.0
      ],
      "notes": "Commercial data from Yukon Escapement Daily Chart.xlsx"
    }
  ]
}