{
  "metadata": {
    "source_file": "archived-excel/20250930_164439_Yukon Escapement Daily Chart.xlsx",
    "conversion_date": "2025-09-30T16:55:35.554464",
    "location": "Andreafsky River (East Fork) Escapement",
    "location_id": "5012",
    "species": "Sockeye Salmon",
    "species_id": "420",
    "method": "escapement",
    "region": "Yukon Management Area",
    "total_records": 35,
    "date_range": {
      "start": "06/20",
      "end": "07/24"
    },
    "adfg_species_code": "S"
  },
  "DATA": [
    {
      "date": "2016-06/20",
      "count": 0,
      "species": "Sockeye Salmon",
      "species_id": "420",
      "adfg_species_code": "S",
      "location": "Andreafsky River (East Fork) Escapement",
      "location_id": "5012",
      "method": "escapement",
      "region": "Yukon Management Area",
      "gps": [
        0.0,
        0.0
      ],
      "notes": "Commercial data from 20250930_164439_Yukon Escapement Daily Chart.xlsx"
    },
    {
      "date": "2016-06/21",
      "count": 0,
      "species": "Sockeye Salmon",
      "species_id": "420",
      "adfg_species_code": "S",
      "location": "Andreafsky River (East Fork) Escapement",
      "location_id": "5012",
      "method": "escapement",
      "region": "Yukon Management Area",
      "gps": [
        0.0,
        0.0
      ],
      "notes": "Commercial data from 20250930_164439_Yukon Escapement Daily Chart.xlsx"
    },
    {
      "date": "2016-06/22",
      "count": 0,
      "species": "Sockeye Salmon",
      "species_id": "420",
      "adfg_species_code": "S",
      "location": "Andreafsky River (East Fork) Escapement",
      "location_id": "5012",
      "method": "escapement",
      "region": "Yukon Management Area",
      "gps": [
        0.0,
        0.0
      ],
      "notes": "Commercial data from 20250930_164439_Yukon Escapement Daily Chart.xlsx"
    },
    {
      "date": "2016-06/23",
      "count": 2,
      "species": "Sockeye Salmon",
      "species_id": "420",
      "adfg_species_code": "S",
      "location": "Andreafsky River (East Fork) Escapement",
      "location_id": "5012",
      "method": "escapement",
      "region": "Yukon Management Area",
      "gps": [
        0.0,
        0.0
      ],
      "notes": "Commercial data from 20250930_164439_Yukon Escapement Daily Chart.xlsx"
    },
    {
      "date": "2016-06/24",
      "count": 14,
      "species": "Sockeye Salmon",
      "species_id": "420",
      "adfg_species_code": "S",
      "location": "Andreafsky River (East Fork) Escapement",
      "location_id": "5012",
      "method": "escapement",
      "region": "Yukon Management Area",
      "gps": [
        0.0,
        0.0
      ],
      "notes": "Commercial data from 20250930_164439_Yukon Escapement Daily Chart.xlsx"
    },
    {
      "date": "2016-06/25",
      "count": 31,
      "species": "Sockeye Salmon",
      "species_id": "420",
      "adfg_species_code": "S",
      "location": "Andreafsky River (East Fork) Escapement",
      "location_id": "5012",
      "method": "escapement",
      "region": "Yukon Management Area",
      "gps": [
        0.0,
        0.0
      ],
      "notes": "Commercial data from 20250930_164439_Yukon Escapement Daily Chart.xlsx"
    },
    {
      "date": "2016-06/26",
      "count": 38,
      "species": "Sockeye Salmon",
      "species_id": "420",
      "adfg_species_code": "S",
      "location": "Andreafsky River (East Fork) Escapement",
      "location_id": "5012",
      "method": "escapement",
      "region": "Yukon Management Area",
      "gps": [
        0.0,
        0.0
      ],
      "notes": "Commercial data from 20250930_164439_Yukon Escapement Daily Chart.xlsx"
    },
    {
      "date": "2016-06/27",
      "count": 58,
      "species": "Sockeye Salmon",
      "species_id": "420",
      "adfg_species_code": "S",
      "location": "Andreafsky River (East Fork) Escapement",
      "location_id": "5012",
      "method": "escapement",
      "region": "Yukon Management Area",
      "gps": [
        0.0,
        0.0
      ],
      "notes": "Commercial data from 20250930_164439_Yukon Escapement Daily Chart.xlsx"
    },
    {
      "date": "2016-06/28",
      "count": 40,
      "species": "Sockeye Salmon",
      "species_id": "420",
      "adfg_species_code": "S",
      "location": "Andreafsky River (East Fork) Escapement",
      "location_id": "5012",
      "method": "escapement",
      "region": "Yukon Management Area",
      "gps": [
        0.0,
        0.0
      ],
      "notes": "Commercial data from 20250930_164439_Yukon Escapement Daily Chart.xlsx"
    },
    {
      "date": "2016-06/29",
      "count": 25,
      "species": "Sockeye Salmon",
      "species_id": "420",
      "adfg_species_code": "S",
      "location": "Andreafsky River (East Fork) Escapement",
      "location_id": "5012",
      "method": "escapement",
      "region": "Yukon Management Area",
      "gps": [
        0.0,
        0.0
      ],
      "notes": "Commercial data from 20250930_164439_Yukon Escapement Daily Chart.xlsx"
    },
    {
      "date": "2016-06/30",
      "count": 31,
      "species": "Sockeye Salmon",
      "species_id": "420",
      "adfg_species_code": "S",
      "location": "Andreafsky River (East Fork) Escapement",
      "location_id": "5012",
      "method": "escapement",
      "region": "Yukon Management Area",
      "gps": [
        0.0,
        0.0
      ],
      "notes": "Commercial data from 20250930_164439_Yukon Escapement Daily Chart.xlsx"
    },
    {
      "date": "2016-07/01",
      "count": 44,
      "species": "Sockeye Salmon",
      "species_id": "420",
      "adfg_species_code": "S",
      "location": "Andreafsky River (East Fork) Escapement",
      "location_id": "5012",
      "method": "escapement",
      "region": "Yukon Management Area",
      "gps": [
        0.0,
        0.0
      ],
      "notes": "Commercial data from 20250930_164439_Yukon Escapement Daily Chart.xlsx"
    },
    {
      "date": "2016-07/02",
      "count": 36,
      "species": "Sockeye Salmon",
      "species_id": "420",
      "adfg_species_code": "S",
      "location": "Andreafsky River (East Fork) Escapement",
      "location_id": "5012",
      "method": "escapement",
      "region": "Yukon Management Area",
      "gps": [
        0.0,
        0.0
      ],
      "notes": "Commercial data from 20250930_164439_Yukon Escapement Daily Chart.xlsx"
    },
    {
      "date": "2016-07/03",
      "count": 18,
      "species": "Sockeye Salmon",
      "species_id": "420",
      "adfg_species_code": "S",
      "location": "Andreafsky River (East Fork) Escapement",
      "location_id": "5012",
      "method": "escapement",
      "region": "Yukon Management Area",
      "gps": [
        0.0,
        0.0
      ],
      "notes": "Commercial data from 20250930_164439_Yukon Escapement Daily Chart.xlsx"
    },
    {
      "date": "2016-07/04",
      "count": 41,
      "species": "Sockeye Salmon",
      "species_id": "420",
      "adfg_species_code": "S",
      "location": "Andreafsky River (East Fork) Escapement",
      "location_id": "5012",
      "method": "escapement",
      "region": "Yukon Management Area",
      "gps": [
        0.0,
        0.0
      ],
      "notes": "Commercial data from 20250930_164439_Yukon Escapement Daily Chart.xlsx"
    },
    {
      "date": "2016-07/05",
      "count": 45,
      "species": "Sockeye Salmon",
      "species_id": "420",
      "adfg_species_code": "S",
      "location": "Andreafsky River (East Fork) Escapement",
      "location_id": "5012",
      "method": "escapement",
      "region": "Yukon Management Area",
      "gps": [
        0.0,
        0.0
      ],
      "notes": "Commercial data from 20250930_164439_Yukon Escapement Daily Chart.xlsx"
    },
    {
      "date": "2016-07/06",
      "count": 61,
      "species": "Sockeye Salmon",
      "species_id": "420",
      "adfg_species_code": "S",
      "location": "Andreafsky River (East Fork) Escapement",
      "location_id": "5012",
      "method": "escapement",
      "region": "Yukon Management Area",
      "gps": [
        0.0,
        0.0
      ],
      "notes": "Commercial data from 20250930_164439_Yukon Escapement Daily Chart.xlsx"
    },
    {
      "date": "2016-07/07",
      "count": 28,
      "species": "Sockeye Salmon",
      "species_id": "420",
      "adfg_species_code": "S",
      "location": "Andreafsky River (East Fork) Escapement",
      "location_id": "5012",
      "method": "escapement",
      "region": "Yukon Management Area",
      "gps": [
        0.0,
        0.0
      ],
      "notes": "Commercial data from 20250930_164439_Yukon Escapement Daily Chart.xlsx"
    },
    {
      "date": "2016-07/08",
      "count": 51,
      "species": "Sockeye Salmon",
      "species_id": "420",
      "adfg_species_code": "S",
      "location": "Andreafsky River (East Fork) Escapement",
      "location_id": "5012",
      "method": "escapement",
      "region": "Yukon Management Area",
      "gps": [
        0.0,
        0.0
      ],
      "notes": "Commercial data from 20250930_164439_Yukon Escapement Daily Chart.xlsx"
    },
    {
      "date": "2016-07/09",
      "count": 54,
      "species": "Sockeye Salmon",
      "species_id": "420",
      "adfg_species_code": "S",
      "location": "Andreafsky River (East Fork) Escapement",
      "location_id": "5012",
      "method": "escapement",
      "region": "Yukon Management Area",
      "gps": [
        0.0,
        0.0
      ],
      "notes": "Commercial data from 20250930_164439_Yukon Escapement Daily Chart.xlsx"
    },
    {
      "date": "2016-07/10",
      "count": 54,
      "species": "Sockeye Salmon",
      "species_id": "420",
      "adfg_species_code": "S",
      "location": "Andreafsky River (East Fork) Escapement",
      "location_id": "5012",
      "method": "escapement",
      "region": "Yukon Management Area",
      "gps": [
        0.0,
        0.0
      ],
      "notes": "Commercial data from 20250930_164439_Yukon Escapement Daily Chart.xlsx"
    },
    {
      "date": "2016-07/11",
      "count": 69,
      "species": "Sockeye Salmon",
      "species_id": "420",
      "adfg_species_code": "S",
      "location": "Andreafsky River (East Fork) Escapement",
      "location_id": "5012",
      "method": "escapement",
      "region": "Yukon Management Area",
      "gps": [
        0.0,
        0.0
      ],
      "notes": "Commercial data from 20250930_164439_Yukon Escapement Daily Chart.xlsx"
    },
    {
      "date": "2016-07/12",
      "count": 51,
      "species": "Sockeye Salmon",
      "species_id": "420",
      "adfg_species_code": "S",
      "location": "Andreafsky River (East Fork) Escapement",
      "location_id": "5012",
      "method": "escapement",
      "region": "Yukon Management Area",
      "gps": [
        0.0,
        0.0
      ],
      "notes": "Commercial data from 20250930_164439_Yukon Escapement Daily Chart.xlsx"
    },
    {
      "date": "2016-07/13",
      "count": 20,
      "species": "Sockeye Salmon",
      "species_id": "420",
      "adfg_species_code": "S",
      "location": "Andreafsky River (East Fork) Escapement",
      "location_id": "5012",
      "method": "escapement",
      "region": "Yukon Management Area",
      "gps": [
        0.0,
        0.0
      ],
      "notes": "Commercial data from 20250930_164439_Yukon Escapement Daily Chart.xlsx"
    },
    {
      "date": "2016-07/14",
      "count": 32,
      "species": "Sockeye Salmon",
      "species_id": "420",
      "adfg_species_code": "S",
      "location": "Andreafsky River (East Fork) Escapement",
      "location_id": "5012",
      "method": "escapement",
      "region": "Yukon Management Area",
      "gps": [
        0.0,
        0.0
      ],
      "notes": "Commercial data from 20250930_164439_Yukon Escapement Daily Chart.xlsx"
    },
    {
      "date": "2016-07/15",
      "count": 39,
      "species": "Sockeye Salmon",
      "species_id": "420",
      "adfg_species_code": "S",
      "location": "Andreafsky River (East Fork) Escapement",
      "location_id": "5012",
      "method": "escapement",
      "region": "Yukon Management Area",
      "gps": [
        0.0,
        0.0
      ],
      "notes": "Commercial data from 20250930_164439_Yukon Escapement Daily Chart.xlsx"
    },
    {
      "date": "2016-07/16",
      "count": 39,
      "species": "Sockeye Salmon",
      "species_id": "420",
      "adfg_species_code": "S",
      "location": "Andreafsky River (East Fork) Escapement",
      "location_id": "5012",
      "method": "escapement",
      "region": "Yukon Management Area",
      "gps": [
        0.0,
        0.0
      ],
      "notes": "Commercial data from 20250930_164439_Yukon Escapement Daily Chart.xlsx"
    },
    {
      "date": "2016-07/17",
      "count": 16,
      "species": "Sockeye Salmon",
      "species_id": "420",
      "adfg_species_code": "S",
      "location": "Andreafsky River (East Fork) Escapement",
      "location_id": "5012",
      "method": "escapement",
      "region": "Yukon Management Area",
      "gps": [
        0.0,
        0.0
      ],
      "notes": "Commercial data from 20250930_164439_Yukon Escapement Daily Chart.xlsx"
    },
    {
      "date": "2016-07/18",
      "count": 13,
      "species": "Sockeye Salmon",
      "species_id": "420",
      "adfg_species_code": "S",
      "location": "Andreafsky River (East Fork) Escapement",
      "location_id": "5012",
      "method": "escapement",
      "region": "Yukon Management Area",
      "gps": [
        0.0,
        0.0
      ],
      "notes": "Commercial data from 20250930_164439_Yukon Escapement Daily Chart.xlsx"
    },
    {
      "date": "2016-07/19",
      "count": 30,
      "species": "Sockeye Salmon",
      "species_id": "420",
      "adfg_species_code": "S",
      "location": "Andreafsky River (East Fork) Escapement",
      "location_id": "5012",
      "method": "escapement",
      "region": "Yukon Management Area",
      "gps": [
        0.0,
        0.0
      ],
      "notes": "Commercial data from 20250930_164439_Yukon Escapement Daily Chart.xlsx"
    },
    {
      "date": "2016-07/20",
      "count": 27,
      "species": "Sockeye Salmon",
      "species_id": "420",
      "adfg_species_code": "S",
      "location": "Andreafsky River (East Fork) Escapement",
      "location_id": "5012",
      "method": "escapement",
      "region": "Yukon Management Area",
      "gps": [
        0.0,
        0.0
      ],
      "notes": "Commercial data from 20250930_164439_Yukon Escapement Daily Chart.xlsx"
    },
    {
      "date": "2016-07/21",
      "count": 14,
      "species": "Sockeye Salmon",
      "species_id": "420",
      "adfg_species_code": "S",
      "location": "Andreafsky River (East Fork) Escapement",
      "location_id": "5012",
      "method": "escapement",
      "region": "Yukon Management Area",
      "gps": [
        0.0,
        0.0
      ],
      "notes": "Commercial data from 20250930_164439_Yukon Escapement Daily Chart.xlsx"
    },
    {
      "date": "2016-07/22",
      "count": 21,
      "species": "Sockeye Salmon",
      "species_id": "420",
      "adfg_species_code": "S",
      "location": "Andreafsky River (East Fork) Escapement",
      "location_id": "5012",
      "method": "escapement",
      "region": "Yukon Management Area",
      "gps": [
        0.0,
        0.0
      ],
      "notes": "Commercial data from 20250930_164439_Yukon Escapement Daily Chart.xlsx"
    },
    {
      "date": "2016-07/23",
      "count": 22,
      "species": "Sockeye Salmon",
      "species_id": "420",
      "adfg_species_code": "S",
      "location": "Andreafsky River (East Fork) Escapement",
      "location_id": "5012",
      "method": "escapement",
      "region": "Yukon Management Area",
      "gps": [
        0.0,
        0.0
      ],
      "notes": "Commercial data from 20250930_164439_Yukon Escapement Daily Chart.xlsx"
    },
    {
      "date": "2016-07/24",
      "count": 7,
      "species": "Sockeye Salmon",
      "species_id": "420",
      "adfg_species_code": "S",
      "location": "Andreafsky River (East Fork) Escapement",
      "location_id": "5012",
      "method": "escapement",
      "region": "Yukon Management Area",
      "gps": [
        0.0,
        0.0
      ],
      "notes": "Commercial data from 20250930_164439_Yukon Escapement Daily Chart.xlsx"
    }
  ]
}